wildfire/__init__.py
wildfire/core.py
wildfire-0.1.dist-info/DESCRIPTION.rst
wildfire-0.1.dist-info/METADATA
wildfire-0.1.dist-info/RECORD
wildfire-0.1.dist-info/WHEEL
wildfire-0.1.dist-info/metadata.json
wildfire-0.1.dist-info/top_level.txt
