Metadata-Version: 2.0
Name: wildfire
Version: 0.1
Summary: A library for automatically generating HTTP services
Home-page: https://github.com/floscha/floscha
Author: Florian Schäfer
Author-email: florian.joh.schaefer@gmail.com
License: Apache Software License
Platform: UNKNOWN
Classifier: Development Status :: 3 - Alpha
Classifier: Intended Audience :: Developers
Classifier: License :: OSI Approved :: MIT License
Classifier: Operating System :: OS Independent
Classifier: Programming Language :: Python :: 3
Classifier: Programming Language :: Python :: 3.6
Classifier: Programming Language :: Python :: 3 :: Only
Classifier: Topic :: Software Development
Requires-Dist: flask (==0.12.2)
